setup.py
TwentyOneCardGame/__init__.py
TwentyOneCardGame/game_settings.py
TwentyOneCardGame/play_game.py
TwentyOneCardGame.egg-info/PKG-INFO
TwentyOneCardGame.egg-info/SOURCES.txt
TwentyOneCardGame.egg-info/dependency_links.txt
TwentyOneCardGame.egg-info/top_level.txt