Metadata-Version: 1.1
Name: TwentyOneCardGame
Version: 1.23
Summary: Basic game of Black Jack/21
Home-page: UNKNOWN
Author: Patrick Löwe
Author-email: patricklowe33@gmail.com
License: MIT
Keywords: GAME,21,BLACK JACK
Platform: UNKNOWN
Classifier: Development Status :: 3 - Alpha
Classifier: Intended Audience :: Developers
Classifier: Topic :: Software Development :: Build Tools
Classifier: License :: OSI Approved :: MIT License
Classifier: Programming Language :: Python :: 3.8
